{
  "title": "PromptlyTechnologies: Zazzle.com Store:",
  "link": "http://www.zazzle.com/z.3/pages/api/find.aspx?ch=promptlytechnologies&ou=%2Fstore%2Fpromptlytechnologies%2Ffeed",
  "description": "",
  "language": "en-us",
  "ttl": 60,
  "opensearch:totalResults": 1,
  "opensearch:startIndex": 1,
  "opensearch:itemsPerPage": 60,
  "opensearch:Query": {
    "@_role": "request",
    "@_searchTerms": ""
  },
  "item": {
    "guid": "https://www.zazzle.com/saturn_surfer_t_shirt-256782080270214030",
    "pubDate": "Sun, 07 May 2023 15:11:03 GMT",
    "title": "Saturn Surfer T-Shirt",
    "link": "https://www.zazzle.com/saturn_surfer_t_shirt-256782080270214030",
    "author": "PromptlyTechnologies",
    "description": "<div class=\"collectionItemCell collectionItemCell-product\"><div class=\"collectionItemCell-main\"><div class=\"collectionItemCell-realview\"><a class=\"collectionItemCell-realviewLink\" href=\"https://www.zazzle.com/saturn_surfer_t_shirt-256782080270214030\"><img class=\"collectionItemCell-image\" src=\"https://rlv.zcache.com/saturn_surfer_t_shirt-r71e635323ea340e5837e7f8cb1a28273_k2gm8_152.jpg\" alt=\"Saturn Surfer T-Shirt\" /></a></div><div class=\"collectionItemCell-info\"><div class=\"collectionItemCell-title\"><a class=\"collectionItemCell-titleLink\" href=\"https://www.zazzle.com/saturn_surfer_t_shirt-256782080270214030\">Saturn Surfer T-Shirt</a></div><div class=\"collectionItemCell-price\">$21.45</div></div></div></div>",
    "price": "$21.45",
    "media:title": "Saturn Surfer T-Shirt",
    "media:description": "An astronaut surfs the golden rings of a planet in outer space—a blue gas giant",
    "media:price": "$21.45",
    "media:thumbnail": {
      "@_url": "https://rlv.zcache.com/saturn_surfer_t_shirt-r71e635323ea340e5837e7f8cb1a28273_k2gm8_152.jpg"
    },
    "media:content": {
      "@_url": "https://rlv.zcache.com/saturn_surfer_t_shirt-r71e635323ea340e5837e7f8cb1a28273_k2gm8_500.jpg"
    },
    "media:keywords": "space, astronaut, planet, sci-fi, science fiction, ringed planet, surfing, orange, blue, surfer",
    "media:rating": {
      "#text": "g",
      "@_scheme": "urn:mpaa"
    }
  }
}